dnnSwift/DNN.py
dnnSwift/DNNWrapperClass.py
dnnSwift/ImageHandler.py
dnnSwift/Validator.py
dnnSwift/__init__.py
dnnSwift-0.3.1.dist-info/DESCRIPTION.rst
dnnSwift-0.3.1.dist-info/METADATA
dnnSwift-0.3.1.dist-info/RECORD
dnnSwift-0.3.1.dist-info/WHEEL
dnnSwift-0.3.1.dist-info/metadata.json
dnnSwift-0.3.1.dist-info/top_level.txt
