Metadata-Version: 2.0
Name: dnnSwift
Version: 0.3.1
Summary: Quick Convolutional Neural Network Implementation
Home-page: https://github.com/DragonDuck/DNNSwift
Author: UNKNOWN
Author-email: UNKNOWN
License: GNU General Public License Version 3
Keywords: Deep Learning,Convolution,Neural Network,DNN,CNN,Classification,Classifier
Platform: UNKNOWN
Requires-Dist: h5py
Requires-Dist: numpy
Requires-Dist: pygraphviz
Requires-Dist: tensorflow
